pyspecies/__init__.py
pyspecies/_euler.py
pyspecies/_utils.py
pyspecies/models.py
pyspecies/pop.py
PySpecies-0.1.2.dist-info/LICENSE
PySpecies-0.1.2.dist-info/METADATA
PySpecies-0.1.2.dist-info/WHEEL
PySpecies-0.1.2.dist-info/top_level.txt
PySpecies-0.1.2.dist-info/RECORD
