Metadata-Version: 2.1
Name: PySpecies
Version: 0.1.2
Summary: Blazing-fast simulation of self-organized patterns in reaction-diffusion systems.
Home-page: https://github.com/samuelbx/pyspecies
Author: Samuel Boïté, Mathias Grau
Author-email: boite.samuel@gmail.com
Classifier: Programming Language :: Python :: 3
Classifier: License :: OSI Approved :: MIT License
Classifier: Operating System :: OS Independent
Requires-Python: >=3.6
License-File: LICENSE
